sphinxcontrib/pseudocode2/__init__.py
sphinxcontrib/pseudocode2/exceptions.py
sphinxcontrib/pseudocode2/version.py
sphinxcontrib_pseudocode2-1.1.2.dist-info/METADATA
sphinxcontrib_pseudocode2-1.1.2.dist-info/WHEEL
sphinxcontrib_pseudocode2-1.1.2.dist-info/licenses/LICENSE.rst
sphinxcontrib_pseudocode2-1.1.2.dist-info/RECORD
