Metadata-Version: 2.4
Name: sphinxcontrib-pseudocode2
Version: 1.1.2
Summary: Sphinx extension to render LaTeX-like pseudocode via pseudocode.js (Sphinx 7.1+/8.x compatible, MathJax 3 friendly, AMD-safe)
Project-URL: Homepage, https://github.com/DeepPSP/sphinxcontrib-pseudocode2
Project-URL: Issues, https://github.com/DeepPSP/sphinxcontrib-pseudocode2/issues
Author-email: WEN Hao <wenh06@gmail.com>
License: | sphinxcontrib-pseudocode is a Sphinx extension for pseudocode.js
License-File: LICENSE.rst
Classifier: Development Status :: 4 - Beta
Classifier: Environment :: Console
Classifier: Environment :: Web Environment
Classifier: Framework :: Sphinx
Classifier: Framework :: Sphinx :: Extension
Classifier: Intended Audience :: Developers
Classifier: License :: OSI Approved :: BSD License
Classifier: Operating System :: OS Independent
Classifier: Programming Language :: Python
Classifier: Programming Language :: Python :: 3
Classifier: Programming Language :: Python :: 3 :: Only
Classifier: Programming Language :: Python :: 3.8
Classifier: Programming Language :: Python :: 3.9
Classifier: Programming Language :: Python :: 3.10
Classifier: Programming Language :: Python :: 3.11
Classifier: Programming Language :: Python :: 3.12
Classifier: Topic :: Documentation
Classifier: Topic :: Utilities
Requires-Python: >=3.8
Requires-Dist: docutils>=0.17
Requires-Dist: jinja2>=3.0
Requires-Dist: sphinx>=7.1
Provides-Extra: dev
Requires-Dist: build; extra == 'dev'
Requires-Dist: furo; extra == 'dev'
Requires-Dist: pydata-sphinx-theme; extra == 'dev'
Requires-Dist: pytest-cov; extra == 'dev'
Requires-Dist: pytest-xdist; extra == 'dev'
Requires-Dist: pytest>=7; extra == 'dev'
Requires-Dist: ruff; extra == 'dev'
Requires-Dist: sphinx; extra == 'dev'
Requires-Dist: sphinx-copybutton; extra == 'dev'
Requires-Dist: sphinx-tabs; extra == 'dev'
Requires-Dist: twine; extra == 'dev'
Provides-Extra: test
Requires-Dist: pytest-cov; extra == 'test'
Requires-Dist: pytest-xdist; extra == 'test'
Requires-Dist: pytest>=7; extra == 'test'
Requires-Dist: sphinx; extra == 'test'
